pms_nvidia_processor/__init__.py
pms_nvidia_processor/processor/base/config.py
pms_nvidia_processor/processor/base/dependency.py
pms_nvidia_processor/processor/base/logger.py
pms_nvidia_processor/processor/base/processor.py
pms_nvidia_processor/processor/cdru_f2/config.py
pms_nvidia_processor/processor/cdru_f2/context.py
pms_nvidia_processor/processor/cdru_f2/processor.py
pms_nvidia_processor/processor/col_en/config.py
pms_nvidia_processor/processor/col_en/context.py
pms_nvidia_processor/processor/col_en/processor.py
pms_nvidia_processor/processor/color_resnet/config.py
pms_nvidia_processor/processor/color_resnet/context.py
pms_nvidia_processor/processor/color_resnet/processor_post.py
pms_nvidia_processor/processor/color_resnet/processor_pre.py
pms_nvidia_processor/processor/do_f3/config.py
pms_nvidia_processor/processor/do_f3/context.py
pms_nvidia_processor/processor/do_f3/processor.py
pms_nvidia_processor/processor/dpir/config.py
pms_nvidia_processor/processor/dpir/context.py
pms_nvidia_processor/processor/dpir/processor.py
pms_nvidia_processor/processor/dru_asm_sr_f3/config.py
pms_nvidia_processor/processor/dru_asm_sr_f3/context.py
pms_nvidia_processor/processor/dru_asm_sr_f3/processor.py
pms_nvidia_processor/processor/dru_rbpn_deinter_f3_gloss/config.py
pms_nvidia_processor/processor/dru_rbpn_deinter_f3_gloss/context.py
pms_nvidia_processor/processor/dru_rbpn_deinter_f3_gloss/processor.py
pms_nvidia_processor/processor/dru_rbpn_deinter_pc_f2/config.py
pms_nvidia_processor/processor/dru_rbpn_deinter_pc_f2/context.py
pms_nvidia_processor/processor/dru_rbpn_deinter_pc_f2/processor.py
pms_nvidia_processor/processor/dru_rbpn_sr_f3/config.py
pms_nvidia_processor/processor/dru_rbpn_sr_f3/context.py
pms_nvidia_processor/processor/dru_rbpn_sr_f3/processor.py
pms_nvidia_processor/processor/dru_rbpn_sr_f5/config.py
pms_nvidia_processor/processor/dru_rbpn_sr_f5/context.py
pms_nvidia_processor/processor/dru_rbpn_sr_f5/processor.py
pms_nvidia_processor-2.11.0.dist-info/METADATA
pms_nvidia_processor-2.11.0.dist-info/WHEEL
pms_nvidia_processor-2.11.0.dist-info/RECORD
