Metadata-Version: 2.4
Name: pms-nvidia-processor
Version: 2.11.0
Summary: lib for pms nvidia processors
Author: HyeongSeok Kim
Author-email: tiryul@gmail.com
Requires-Python: ==3.12.*
Classifier: Programming Language :: Python :: 3
Classifier: Programming Language :: Python :: 3.12
Requires-Dist: albumentations (>=1.4.13,<2.0.0)
Requires-Dist: loguru
Requires-Dist: numpy
Requires-Dist: pms-inference-engine (>=2.0.0,<2.1.0)
Requires-Dist: pms-tensorrt (>=2.1.3,<2.2.0)
